mcp_http/__init__.py
mcp_http/__main__.py
mcp_http/config.py
mcp_http/server.py
mcp_http/server3.py
mcp_http-0.1.3.dist-info/METADATA
mcp_http-0.1.3.dist-info/WHEEL
mcp_http-0.1.3.dist-info/entry_points.txt
mcp_http-0.1.3.dist-info/licenses/LICENSE
mcp_http-0.1.3.dist-info/RECORD
