Metadata-Version: 2.4
Name: mcp-http
Version: 0.1.3
Summary: Add your description here
Author-email: Admin <lighttomorrow2012@hotmail.com>
License-File: LICENSE
Requires-Python: >=3.10
Requires-Dist: fastmcp[cli]>=2.3.1
Requires-Dist: httpx>=0.28.1
